[
    {
        "file": "tracks/Dirty Palm - Ropes (feat. Chandler Jewels) [NCS Release].mp3",
        "cover": "/resources/Record.png",
        "album": "Unknown",
        "song": "Dirty Palm - Ropes (feat. Chandler Jewels) [NCS Release].mp3",
        "artist": "Unknown"
    },
    {
        "file": "tracks/Koven - Looking For More [NCS Release].mp3",
        "cover": "/resources/Record.png",
        "album": "Unknown",
        "song": "Koven - Looking For More [NCS Release].mp3",
        "artist": "Unknown"
    },
    {
        "file": "tracks/Arc North - Symphony (feat. Donna Tella) [NCS Release].mp3",
        "cover": "/resources/Record.png",
        "album": "Unknown",
        "song": "Arc North - Symphony (feat. Donna Tella) [NCS Release].mp3",
        "artist": "Unknown"
    },
    {
        "file": "tracks/Dirty Palm - Ropes (feat. Chandler Jewels) [NCS Release] (1).mp3",
        "cover": "/resources/Record.png",
        "album": "Unknown",
        "song": "Dirty Palm - Ropes (feat. Chandler Jewels) [NCS Release] (1).mp3",
        "artist": "Unknown"
    }
]